doker/__init__.py
doker/fileutils.py
doker/generate.py
doker/log.py
doker/main.py
doker/preprocess.py
doker/rst2pdf/__init__.py
doker/rst2pdf/aafigure_directive.py
doker/rst2pdf/basenodehandler.py
doker/rst2pdf/config.py
doker/rst2pdf/counter_off_role.py
doker/rst2pdf/counter_role.py
doker/rst2pdf/createpdf.py
doker/rst2pdf/dumpstyle.py
doker/rst2pdf/findfonts.py
doker/rst2pdf/flowables.py
doker/rst2pdf/genelements.py
doker/rst2pdf/genpdftext.py
doker/rst2pdf/image.py
doker/rst2pdf/languages.py
doker/rst2pdf/log.py
doker/rst2pdf/math_directive.py
doker/rst2pdf/math_flowable.py
doker/rst2pdf/nodehandlers.py
doker/rst2pdf/noop_directive.py
doker/rst2pdf/oddeven_directive.py
doker/rst2pdf/opt_imports.py
doker/rst2pdf/pdfbuilder.py
doker/rst2pdf/pygments2style.py
doker/rst2pdf/pygments_code_block_directive.py
doker/rst2pdf/rson.py
doker/rst2pdf/sectnumlinks.py
doker/rst2pdf/sinker.py
doker/rst2pdf/sphinxnodes.py
doker/rst2pdf/styles.py
doker/rst2pdf/svgimage.py
doker/rst2pdf/utils.py
doker/rst2pdf/writer.py
doker/rst2pdf/extensions/__init__.py
doker/rst2pdf/extensions/dotted_toc.py
doker/rst2pdf/extensions/fancytitles.py
doker/rst2pdf/extensions/inkscape_r2p.py
doker/rst2pdf/extensions/plantuml.py
doker/rst2pdf/extensions/preprocess_r2p.py
doker/rst2pdf/extensions/sample.py
doker/rst2pdf/extensions/vectorpdf_r2p.py
doker/rst2pdf/images/image-missing.jpg
doker/rst2pdf/images/image-missing.png
doker/rst2pdf/styles/11x17.style
doker/rst2pdf/styles/a0.style
doker/rst2pdf/styles/a1-landscape.style
doker/rst2pdf/styles/a1.style
doker/rst2pdf/styles/a2-landscape.style
doker/rst2pdf/styles/a2.style
doker/rst2pdf/styles/a3-landscape.style
doker/rst2pdf/styles/a3.style
doker/rst2pdf/styles/a4-landscape.style
doker/rst2pdf/styles/a4.style
doker/rst2pdf/styles/a5-landscape.style
doker/rst2pdf/styles/a5.style
doker/rst2pdf/styles/a6-landscape.style
doker/rst2pdf/styles/a6.style
doker/rst2pdf/styles/autumn.style
doker/rst2pdf/styles/b0.style
doker/rst2pdf/styles/b1-landscape.style
doker-0.2.0.dist-info/LICENSE
doker-0.2.0.dist-info/METADATA
doker-0.2.0.dist-info/WHEEL
doker-0.2.0.dist-info/entry_points.txt
doker-0.2.0.dist-info/top_level.txt
doker-0.2.0.dist-info/RECORD
