Metadata-Version: 1.1
Name: doker
Version: 0.2.0
Summary: Rich PDF documents creating tool
Home-page: https://github.com/doker-project/doker
Author: Shamil Yakupov
Author-email: UNKNOWN
License: UNKNOWN
Platform: UNKNOWN
Classifier: Programming Language :: Python :: 3
Classifier: License :: OSI Approved :: MIT License
Classifier: Operating System :: OS Independent
